kqhivemind_hivebox/__init__.py
kqhivemind_hivebox/__main__.py
kqhivemind_hivebox/__version__.py
kqhivemind_hivebox/constants.py
kqhivemind_hivebox/gamestate.py
kqhivemind_hivebox/gpio.py
kqhivemind_hivebox/lcddriver.py
kqhivemind_hivebox/taptest.py
kqhivemind_hivebox/util.py
kqhivemind_hivebox-1.1.6.dist-info/entry_points.txt
kqhivemind_hivebox-1.1.6.dist-info/WHEEL
kqhivemind_hivebox-1.1.6.dist-info/METADATA
kqhivemind_hivebox-1.1.6.dist-info/RECORD
