Metadata-Version: 2.1
Name: kqhivemind_hivebox
Version: 1.1.6
Summary: HiveMind NFC reader client for HiveBox
Author-email: KQHiveMind <contact@kqhivemind.com>
Classifier: License :: OSI Approved :: MIT License
Requires-Dist: gpiod==2.2.1
Requires-Dist: nfcpy==1.0.3
Requires-Dist: requests==2.31.0
Requires-Dist: py532lib==2018.6.14.dev1
Requires-Dist: websocket-client==1.2.1
Project-URL: Home, https://kqhivemind.com
